remodels/__init__.py
remodels/data/EntsoeApi.py
remodels/data/__init__.py
remodels/pipelines/RePipeline.py
remodels/pipelines/__init__.py
remodels/pointsModels/PointModel.py
remodels/pointsModels/__init__.py
remodels/py.typed
remodels/qra/__init__.py
remodels/qra/_functions.py
remodels/qra/_linear_model.py
remodels/qra/_lstsq.py
remodels/qra/fqra.py
remodels/qra/fqrm.py
remodels/qra/lqra.py
remodels/qra/qra.py
remodels/qra/qrm.py
remodels/qra/sfqra.py
remodels/qra/sfqrm.py
remodels/qra/sqra.py
remodels/qra/sqrm.py
remodels/qra/tester/__init__.py
remodels/qra/tester/qr_results_summary.py
remodels/qra/tester/qr_tester.py
remodels/transformers/BaseScaler.py
remodels/transformers/DSTAdjuster.py
remodels/transformers/StandardizingScaler.py
remodels/transformers/VSTransformers/ArcsinhScaler.py
remodels/transformers/VSTransformers/BoxCoxScaler.py
remodels/transformers/VSTransformers/ClippingScaler.py
remodels/transformers/VSTransformers/LogClippingScaler.py
remodels/transformers/VSTransformers/LogisticScaler.py
remodels/transformers/VSTransformers/MLogScaler.py
remodels/transformers/VSTransformers/PITScaler.py
remodels/transformers/VSTransformers/PolyScaler.py
remodels/transformers/VSTransformers/__init__.py
remodels/transformers/__init__.py
remodels-1.0.1.dist-info/entry_points.txt
remodels-1.0.1.dist-info/LICENSE.txt
remodels-1.0.1.dist-info/WHEEL
remodels-1.0.1.dist-info/METADATA
remodels-1.0.1.dist-info/RECORD
