Metadata-Version: 2.1
Name: remodels
Version: 1.0.1
Summary: remodels
Home-page: https://github.com/zakrzewow/remodels
License: MIT
Author: Grzegorz Zakrzewski
Author-email: zakrzew12@gmail.com
Requires-Python: >=3.8,<4.0
Classifier: Development Status :: 3 - Alpha
Classifier: License :: OSI Approved :: MIT License
Classifier: Programming Language :: Python :: 3
Classifier: Programming Language :: Python :: 3.10
Classifier: Programming Language :: Python :: 3.8
Classifier: Programming Language :: Python :: 3.9
Requires-Dist: matplotlib (>=3.7.0,<3.8.0)
Requires-Dist: pandas (<=1.5.3)
Requires-Dist: scikit-learn (>=1.3.1,<2.0.0)
Requires-Dist: tqdm (>=4.66.1,<5.0.0)
Project-URL: Changelog, https://github.com/zakrzewow/remodels/releases
Project-URL: Documentation, https://remodels.readthedocs.io
Project-URL: Repository, https://github.com/zakrzewow/remodels
